rrct/__init__.py
rrct/algorithm.py
rrct/utils.py
rrct-1.0.5.dist-info/LICENSE
rrct-1.0.5.dist-info/METADATA
rrct-1.0.5.dist-info/WHEEL
rrct-1.0.5.dist-info/top_level.txt
rrct-1.0.5.dist-info/RECORD
