Metadata-Version: 2.1
Name: rrct
Version: 1.0.5
Summary: Relevance, Redundancy, and Complementarity Trade-off, a robust feature selection algorithm.
Home-page: https://github.com/Rasheed19/rrct-modification
Author: Rasheed Ibraheem
Author-email: R.O.Ibraheem@sms.ed.ac.uk
Maintainer: Rasheed Ibraheem
Maintainer-email: R.O.Ibraheem@sms.ed.ac.uk
License: CC-BY-4.0
Classifier: Programming Language :: Python :: 3
Classifier: License :: OSI Approved :: GNU General Public License v3 (GPLv3)
Classifier: Operating System :: OS Independent
Requires-Python: >=3.10
License-File: LICENSE
Requires-Dist: numpy
Requires-Dist: pandas
Requires-Dist: scikit-learn
Requires-Dist: pingouin
Requires-Dist: openpyxl
